{"add":{"path":"part-00000-dafe3d98-d9e0-4740-b74c-cde2338fe388-c000.snappy.parquet","partitionValues":{},"size":394,"modificationTime":1668387595211,"dataChange":true,"stats":"{\"numRecords\":0,\"minValues\":{},\"maxValues\":{},\"nullCount\":{}}"}}
{"add":{"path":"part-00001-6f4765d9-de6f-4959-ab54-1d90a0c67710-c000.snappy.parquet","partitionValues":{},"size":691,"modificationTime":1668387595219,"dataChange":true,"stats":"{\"numRecords\":1,\"minValues\":{\"id\":1,\"Department\":\"IT\"},\"maxValues\":{\"id\":1,\"Department\":\"IT\"},\"nullCount\":{\"id\":0,\"Department\":0}}"}}
{"add":{"path":"part-00003-f633ceb8-350c-4c4a-891f-d858a39a8263-c000.snappy.parquet","partitionValues":{},"size":740,"modificationTime":1668387595203,"dataChange":true,"stats":"{\"numRecords\":1,\"minValues\":{\"id\":2,\"Department\":\"Marketing\"},\"maxValues\":{\"id\":2,\"Department\":\"Marketing\"},\"nullCount\":{\"id\":0,\"Department\":0}}"}}
{"add":{"path":"part-00005-207923a5-e46f-4409-a7a4-326a7ea5822d-c000.snappy.parquet","partitionValues":{},"size":782,"modificationTime":1668387595215,"dataChange":true,"stats":"{\"numRecords\":1,\"minValues\":{\"id\":3,\"Department\":\"Human Resources\"},\"maxValues\":{\"id\":3,\"Department\":\"Human Resources\"},\"nullCount\":{\"id\":0,\"Department\":0}}"}}
{"add":{"path":"part-00007-ffa14669-1ff8-4971-b8e7-a27328b5ec5b-c000.snappy.parquet","partitionValues":{},"size":712,"modificationTime":1668387595223,"dataChange":true,"stats":"{\"numRecords\":1,\"minValues\":{\"id\":4,\"Department\":\"Sales\"},\"maxValues\":{\"id\":4,\"Department\":\"Sales\"},\"nullCount\":{\"id\":0,\"Department\":0}}"}}
{"remove":{"path":"part-00000-e3f687f0-d4bc-4be2-8560-2a89032f9936-c000.snappy.parquet","deletionTimestamp":1668387595524,"dataChange":true,"extendedFileMetadata":true,"partitionValues":{},"size":394}}
{"remove":{"path":"part-00007-b0058007-924d-4748-b0ca-8cf302c4d47b-c000.snappy.parquet","deletionTimestamp":1668387595524,"dataChange":true,"extendedFileMetadata":true,"partitionValues":{},"size":712}}
{"remove":{"path":"part-00003-a4263d5e-809d-4f7d-aff2-60b43197e430-c000.snappy.parquet","deletionTimestamp":1668387595524,"dataChange":true,"extendedFileMetadata":true,"partitionValues":{},"size":740}}
{"remove":{"path":"part-00005-05bfb3b0-091b-4ebe-88b5-8c479d69276f-c000.snappy.parquet","deletionTimestamp":1668387595524,"dataChange":true,"extendedFileMetadata":true,"partitionValues":{},"size":782}}
{"remove":{"path":"part-00001-c8d1d81b-41a7-4e00-8ecd-2bd65351311a-c000.snappy.parquet","deletionTimestamp":1668387595524,"dataChange":true,"extendedFileMetadata":true,"partitionValues":{},"size":691}}
{"commitInfo":{"timestamp":1668387595525,"operation":"WRITE","operationParameters":{"mode":"Overwrite","partitionBy":"[]"},"readVersion":1,"isolationLevel":"Serializable","isBlindAppend":false,"operationMetrics":{"numFiles":"5","numOutputRows":"4","numOutputBytes":"3319"},"engineInfo":"Apache-Spark/3.3.0 Delta-Lake/2.1.1","txnId":"8e05fcb5-a6e9-4388-97aa-7f37d23a7746"}}
